vetr_summarizer/__init__.py
vetr_summarizer/__main__.py
vetr_summarizer/config.py
vetr_summarizer/main.py
vetr_summarizer/config/excluded_keys
vetr_summarizer/templates/base.j2
vetr_summarizer/templates/vetr-data.j2
vetr_summarizer-0.3.4.data/data/vetr-summarizer/base.j2
vetr_summarizer-0.3.4.data/data/vetr-summarizer/excluded_keys
vetr_summarizer-0.3.4.data/data/vetr-summarizer/vetr-data.j2
vetr_summarizer-0.3.4.dist-info/AUTHORS.md
vetr_summarizer-0.3.4.dist-info/LICENSE
vetr_summarizer-0.3.4.dist-info/METADATA
vetr_summarizer-0.3.4.dist-info/WHEEL
vetr_summarizer-0.3.4.dist-info/entry_points.txt
vetr_summarizer-0.3.4.dist-info/top_level.txt
vetr_summarizer-0.3.4.dist-info/RECORD
