Metadata-Version: 2.2
Name: vetr-summarizer
Version: 0.3.4
Summary: A Python package for visualizing ACI vetR JSON data
Author-email: Osama Abbas <oabbas2512@gmail.com>
Maintainer-email: Osama Abbas <oabbas2512@gmail.com>
License: MIT
Project-URL: homepage, https://pypi.org/project/vetr-summarizer/
Project-URL: Repository, https://github.com/Tes3awy/vetr-summarizer
Project-URL: download, https://github.com/Tes3awy/vetr-summarizer/archive/refs/tags/0.3.4.zip
Project-URL: changelog, https://github.com/Tes3awy/vetr-summarizer/blob/main/CHANGELOG.md
Project-URL: issues, https://github.com/Tes3awy/vetr-summarizer/issues
Project-URL: Say Thanks!, https://saythanks.io/to/Tes3awy
Keywords: Cisco,ACI,automation,vetr-collector,devnet,datacenter,summarizer,JSON
Platform: any
Classifier: Development Status :: 5 - Production/Stable
Classifier: Environment :: Console
Classifier: Intended Audience :: Developers
Classifier: Intended Audience :: System Administrators
Classifier: Topic :: Software Development :: Libraries :: Python Modules
Classifier: Topic :: Software Development :: Quality Assurance
Classifier: Topic :: System :: Networking :: Monitoring
Classifier: Topic :: System :: Systems Administration
Classifier: License :: OSI Approved :: MIT License
Classifier: Natural Language :: English
Classifier: Operating System :: OS Independent
Classifier: Programming Language :: Python :: 3 :: Only
Classifier: Programming Language :: Python :: 3.9
Classifier: Programming Language :: Python :: 3.10
Classifier: Programming Language :: Python :: 3.11
Classifier: Programming Language :: Python :: 3.12
Classifier: Programming Language :: Python :: 3.13
Classifier: Typing :: Typed
Requires-Python: <4,>=3.9.0
License-File: LICENSE
License-File: AUTHORS.md
Requires-Dist: jinja2>=3.1.0; python_version >= "3.9"
Provides-Extra: dev
Requires-Dist: pre-commit; extra == "dev"
Requires-Dist: bumpver; extra == "dev"
Requires-Dist: black; extra == "dev"
Requires-Dist: isort; extra == "dev"
